flake8_import_order_ruler501/__init__.py
flake8_import_order_ruler501/import_order.py
flake8_import_order_ruler501-0.18.1.2.dist-info/LICENSE
flake8_import_order_ruler501-0.18.1.2.dist-info/METADATA
flake8_import_order_ruler501-0.18.1.2.dist-info/WHEEL
flake8_import_order_ruler501-0.18.1.2.dist-info/entry_points.txt
flake8_import_order_ruler501-0.18.1.2.dist-info/top_level.txt
flake8_import_order_ruler501-0.18.1.2.dist-info/RECORD
