Metadata-Version: 2.1
Name: flake8-import-order-ruler501
Version: 0.18.1.2
Summary: ruler501's flake8-import-order plugin.
Home-page: https://github.com/ruler501/flake8-import-order-ruler501
Author: ruler501
Author-email: ruler501@ruler501.com
License: MIT
Keywords: flake8-import-order ruler501
Platform: UNKNOWN
Classifier: Development Status :: 5 - Production/Stable
Classifier: Framework :: Flake8
Classifier: Intended Audience :: Developers
Classifier: License :: OSI Approved :: MIT License
Classifier: Operating System :: OS Independent
Classifier: Programming Language :: Python :: 3.4
Classifier: Programming Language :: Python :: 3.5
Classifier: Programming Language :: Python :: 3.6
Classifier: Programming Language :: Python :: 3.7
Classifier: Topic :: Software Development :: Libraries :: Python Modules
Classifier: Topic :: Software Development :: Quality Assurance
Requires-Python: >=3.4
Requires-Dist: flake8-import-order (>=0.18)
